config/__init__.py
config/env.py
db_integrations/__init__.py
db_integrations/amazon_s3.py
db_integrations/azure_blob.py
db_integrations/cosmos_db.py
db_integrations/sqlalchemy_db.py
llm_integrations/__init__.py
llm_integrations/azure_openai.py
llm_integrations/gemini.py
llm_integrations/llm_initiate.py
llm_integrations/nvidia.py
llm_integrations/open_ai.py
llm_checks_common_functions-1.1.dist-info/METADATA
llm_checks_common_functions-1.1.dist-info/WHEEL
llm_checks_common_functions-1.1.dist-info/top_level.txt
llm_checks_common_functions-1.1.dist-info/RECORD
