Metadata-Version: 2.1
Name: llm_checks_common_functions
Version: 1.1
Summary: common functions, utilities using multiple DB and LLM options.
Home-page: https://pactera1us.visualstudio.com/DefaultCollection/LLM_CoE/_git/redteaming_service
Author: Karthik M
Author-email: karthik.manne@centific.com
Classifier: Programming Language :: Python :: 3
Classifier: License :: OSI Approved :: MIT License
Classifier: Operating System :: OS Independent
Requires-Python: >=3.9
Requires-Dist: langchain ==0.2.11
Requires-Dist: langchain-community
Requires-Dist: openpyxl ==3.1.2
Requires-Dist: pandas ==2.2.1
Requires-Dist: PyYAML
Requires-Dist: tqdm ==4.66.2
Requires-Dist: azure-cosmos
Requires-Dist: azure-storage-blob
Requires-Dist: python-dotenv
Requires-Dist: openai ==0.28
Requires-Dist: langchain-nvidia-ai-endpoints
Requires-Dist: google-generativeai
Requires-Dist: boto3
Requires-Dist: SQLAlchemy ==2.0.29
Requires-Dist: mysql-connector
Requires-Dist: xlsxwriter
Requires-Dist: tiktoken
